{
	"AprilFools":
	{
		"chance": 0,
		"Message":
		[
			{"message":"Happy April Fools day! From the Chance Cubes Team!"},
      {"message":"Oh! The cage! Almost forgot.", "delay":170}
		],
    "Block":
    [
      {"XOffSet":-2,"YOffSet":-1,"ZOffSet":-2,"Block":"minecraft:bedrock", "Falling":false, "RelativeToPlayer":true},
      {"XOffSet":-2,"YOffSet":-1,"ZOffSet":-2,"Block":"minecraft:air", "Falling":false, "delay":200, "RelativeToPlayer":true},
      {"XOffSet":-1,"YOffSet":-1,"ZOffSet":-2,"Block":"minecraft:bedrock", "Falling":false, "RelativeToPlayer":true},
      {"XOffSet":-1,"YOffSet":-1,"ZOffSet":-2,"Block":"minecraft:air", "Falling":false, "delay":200, "RelativeToPlayer":true},
      {"XOffSet":0,"YOffSet":-1,"ZOffSet":-2,"Block":"minecraft:bedrock", "Falling":false, "RelativeToPlayer":true},
      {"XOffSet":0,"YOffSet":-1,"ZOffSet":-2,"Block":"minecraft:air", "Falling":false, "delay":200, "RelativeToPlayer":true},
      {"XOffSet":1,"YOffSet":-1,"ZOffSet":-2,"Block":"minecraft:bedrock", "Falling":false, "RelativeToPlayer":true},
      {"XOffSet":1,"YOffSet":-1,"ZOffSet":-2,"Block":"minecraft:air", "Falling":false, "delay":200, "RelativeToPlayer":true},
      {"XOffSet":2,"YOffSet":-1,"ZOffSet":-2,"Block":"minecraft:bedrock", "Falling":false, "RelativeToPlayer":true},
      {"XOffSet":2,"YOffSet":-1,"ZOffSet":-2,"Block":"minecraft:air", "Falling":false, "delay":200, "RelativeToPlayer":true},

      {"XOffSet":-2,"YOffSet":-1,"ZOffSet":-1,"Block":"minecraft:bedrock", "Falling":false, "RelativeToPlayer":true},
      {"XOffSet":-2,"YOffSet":-1,"ZOffSet":-1,"Block":"minecraft:air", "Falling":false, "delay":200, "RelativeToPlayer":true},
      {"XOffSet":-1,"YOffSet":-1,"ZOffSet":-1,"Block":"minecraft:bedrock", "Falling":false, "RelativeToPlayer":true},
      {"XOffSet":-1,"YOffSet":-1,"ZOffSet":-1,"Block":"minecraft:air", "Falling":false, "delay":200, "RelativeToPlayer":true},
      {"XOffSet":0,"YOffSet":-1,"ZOffSet":-1,"Block":"minecraft:bedrock", "Falling":false, "RelativeToPlayer":true},
      {"XOffSet":0,"YOffSet":-1,"ZOffSet":-1,"Block":"minecraft:air", "Falling":false, "delay":200, "RelativeToPlayer":true},
      {"XOffSet":1,"YOffSet":-1,"ZOffSet":-1,"Block":"minecraft:bedrock", "Falling":false, "RelativeToPlayer":true},
      {"XOffSet":1,"YOffSet":-1,"ZOffSet":-1,"Block":"minecraft:air", "Falling":false, "delay":200, "RelativeToPlayer":true},
      {"XOffSet":2,"YOffSet":-1,"ZOffSet":-1,"Block":"minecraft:bedrock", "Falling":false, "RelativeToPlayer":true},
      {"XOffSet":2,"YOffSet":-1,"ZOffSet":-1,"Block":"minecraft:air", "Falling":false, "delay":200, "RelativeToPlayer":true},

      {"XOffSet":-2,"YOffSet":-1,"ZOffSet":0,"Block":"minecraft:bedrock", "Falling":false, "RelativeToPlayer":true},
      {"XOffSet":-2,"YOffSet":-1,"ZOffSet":0,"Block":"minecraft:air", "Falling":false, "delay":200, "RelativeToPlayer":true},
      {"XOffSet":-1,"YOffSet":-1,"ZOffSet":0,"Block":"minecraft:bedrock", "Falling":false, "RelativeToPlayer":true},
      {"XOffSet":-1,"YOffSet":-1,"ZOffSet":0,"Block":"minecraft:air", "Falling":false, "delay":200, "RelativeToPlayer":true},
      {"XOffSet":0,"YOffSet":-1,"ZOffSet":0,"Block":"minecraft:bedrock", "Falling":false, "RelativeToPlayer":true},
      {"XOffSet":0,"YOffSet":-1,"ZOffSet":0,"Block":"minecraft:air", "Falling":false, "delay":200, "RelativeToPlayer":true},
      {"XOffSet":1,"YOffSet":-1,"ZOffSet":0,"Block":"minecraft:bedrock", "Falling":false, "RelativeToPlayer":true},
      {"XOffSet":1,"YOffSet":-1,"ZOffSet":0,"Block":"minecraft:air", "Falling":false, "delay":200, "RelativeToPlayer":true},
      {"XOffSet":2,"YOffSet":-1,"ZOffSet":0,"Block":"minecraft:bedrock", "Falling":false, "RelativeToPlayer":true},
      {"XOffSet":2,"YOffSet":-1,"ZOffSet":0,"Block":"minecraft:air", "Falling":false, "delay":200, "RelativeToPlayer":true},

      {"XOffSet":-2,"YOffSet":-1,"ZOffSet":1,"Block":"minecraft:bedrock", "Falling":false, "RelativeToPlayer":true},
      {"XOffSet":-2,"YOffSet":-1,"ZOffSet":1,"Block":"minecraft:air", "Falling":false, "delay":200, "RelativeToPlayer":true},
      {"XOffSet":-1,"YOffSet":-1,"ZOffSet":1,"Block":"minecraft:bedrock", "Falling":false, "RelativeToPlayer":true},
      {"XOffSet":-1,"YOffSet":-1,"ZOffSet":1,"Block":"minecraft:air", "Falling":false, "delay":200, "RelativeToPlayer":true},
      {"XOffSet":0,"YOffSet":-1,"ZOffSet":1,"Block":"minecraft:bedrock", "Falling":false, "RelativeToPlayer":true},
      {"XOffSet":0,"YOffSet":-1,"ZOffSet":1,"Block":"minecraft:air", "Falling":false, "delay":200, "RelativeToPlayer":true},
      {"XOffSet":1,"YOffSet":-1,"ZOffSet":1,"Block":"minecraft:bedrock", "Falling":false, "RelativeToPlayer":true},
      {"XOffSet":1,"YOffSet":-1,"ZOffSet":1,"Block":"minecraft:air", "Falling":false, "delay":200, "RelativeToPlayer":true},
      {"XOffSet":2,"YOffSet":-1,"ZOffSet":1,"Block":"minecraft:bedrock", "Falling":false, "RelativeToPlayer":true},
      {"XOffSet":2,"YOffSet":-1,"ZOffSet":1,"Block":"minecraft:air", "Falling":false, "delay":200, "RelativeToPlayer":true},

      {"XOffSet":-2,"YOffSet":-1,"ZOffSet":2,"Block":"minecraft:bedrock", "Falling":false, "RelativeToPlayer":true},
      {"XOffSet":-2,"YOffSet":-1,"ZOffSet":2,"Block":"minecraft:air", "Falling":false, "delay":200, "RelativeToPlayer":true},
      {"XOffSet":-1,"YOffSet":-1,"ZOffSet":2,"Block":"minecraft:bedrock", "Falling":false, "RelativeToPlayer":true},
      {"XOffSet":-1,"YOffSet":-1,"ZOffSet":2,"Block":"minecraft:air", "Falling":false, "delay":200, "RelativeToPlayer":true},
      {"XOffSet":0,"YOffSet":-1,"ZOffSet":2,"Block":"minecraft:bedrock", "Falling":false, "RelativeToPlayer":true},
      {"XOffSet":0,"YOffSet":-1,"ZOffSet":2,"Block":"minecraft:air", "Falling":false, "delay":200, "RelativeToPlayer":true},
      {"XOffSet":1,"YOffSet":-1,"ZOffSet":2,"Block":"minecraft:bedrock", "Falling":false, "RelativeToPlayer":true},
      {"XOffSet":1,"YOffSet":-1,"ZOffSet":2,"Block":"minecraft:air", "Falling":false, "delay":200, "RelativeToPlayer":true},
      {"XOffSet":2,"YOffSet":-1,"ZOffSet":2,"Block":"minecraft:bedrock", "Falling":false, "RelativeToPlayer":true},
      {"XOffSet":2,"YOffSet":-1,"ZOffSet":2,"Block":"minecraft:air", "Falling":false, "delay":200, "RelativeToPlayer":true},

      {"XOffSet":-2,"YOffSet":-1,"ZOffSet":-2,"Block":"minecraft:bedrock", "Falling":false, "RelativeToPlayer":true},
      {"XOffSet":-2,"YOffSet":-1,"ZOffSet":-2,"Block":"minecraft:air", "Falling":false, "delay":200, "RelativeToPlayer":true},
      {"XOffSet":-1,"YOffSet":-1,"ZOffSet":-2,"Block":"minecraft:bedrock", "Falling":false, "RelativeToPlayer":true},
      {"XOffSet":-1,"YOffSet":-1,"ZOffSet":-2,"Block":"minecraft:air", "Falling":false, "delay":200, "RelativeToPlayer":true},
      {"XOffSet":0,"YOffSet":-1,"ZOffSet":-2,"Block":"minecraft:bedrock", "Falling":false, "RelativeToPlayer":true},
      {"XOffSet":0,"YOffSet":-1,"ZOffSet":-2,"Block":"minecraft:air", "Falling":false, "delay":200, "RelativeToPlayer":true},
      {"XOffSet":1,"YOffSet":-1,"ZOffSet":-2,"Block":"minecraft:bedrock", "Falling":false, "RelativeToPlayer":true},
      {"XOffSet":1,"YOffSet":-1,"ZOffSet":-2,"Block":"minecraft:air", "Falling":false, "delay":200, "RelativeToPlayer":true},
      {"XOffSet":2,"YOffSet":-1,"ZOffSet":-2,"Block":"minecraft:bedrock", "Falling":false, "RelativeToPlayer":true},
      {"XOffSet":2,"YOffSet":-1,"ZOffSet":-2,"Block":"minecraft:air", "Falling":false, "delay":200, "RelativeToPlayer":true},

      {"XOffSet":-2,"YOffSet":3, "ZOffSet":-1,"Block":"minecraft:bedrock", "Falling":false, "RelativeToPlayer":true},
      {"XOffSet":-2,"YOffSet":3,"ZOffSet":-1,"Block":"minecraft:air", "Falling":false, "delay":200, "RelativeToPlayer":true},
      {"XOffSet":-1,"YOffSet":3,"ZOffSet":-1,"Block":"minecraft:bedrock", "Falling":false, "RelativeToPlayer":true},
      {"XOffSet":-1,"YOffSet":3,"ZOffSet":-1,"Block":"minecraft:air", "Falling":false, "delay":200, "RelativeToPlayer":true},
      {"XOffSet":0,"YOffSet":3,"ZOffSet":-1,"Block":"minecraft:bedrock", "Falling":false, "RelativeToPlayer":true},
      {"XOffSet":0,"YOffSet":3,"ZOffSet":-1,"Block":"minecraft:air", "Falling":false, "delay":200, "RelativeToPlayer":true},
      {"XOffSet":1,"YOffSet":3,"ZOffSet":-1,"Block":"minecraft:bedrock", "Falling":false, "RelativeToPlayer":true},
      {"XOffSet":1,"YOffSet":3,"ZOffSet":-1,"Block":"minecraft:air", "Falling":false, "delay":200, "RelativeToPlayer":true},
      {"XOffSet":2,"YOffSet":3,"ZOffSet":-1,"Block":"minecraft:bedrock", "Falling":false, "RelativeToPlayer":true},
      {"XOffSet":2,"YOffSet":3,"ZOffSet":-1,"Block":"minecraft:air", "Falling":false, "delay":200, "RelativeToPlayer":true},

      {"XOffSet":-2,"YOffSet":3,"ZOffSet":0,"Block":"minecraft:bedrock", "Falling":false, "RelativeToPlayer":true},
      {"XOffSet":-2,"YOffSet":3,"ZOffSet":0,"Block":"minecraft:air", "Falling":false, "delay":200, "RelativeToPlayer":true},
      {"XOffSet":-1,"YOffSet":3,"ZOffSet":0,"Block":"minecraft:bedrock", "Falling":false, "RelativeToPlayer":true},
      {"XOffSet":-1,"YOffSet":3,"ZOffSet":0,"Block":"minecraft:air", "Falling":false, "delay":200, "RelativeToPlayer":true},
      {"XOffSet":0,"YOffSet":3,"ZOffSet":0,"Block":"minecraft:bedrock", "Falling":false, "RelativeToPlayer":true},
      {"XOffSet":0,"YOffSet":3,"ZOffSet":0,"Block":"minecraft:air", "Falling":false, "delay":200, "RelativeToPlayer":true},
      {"XOffSet":1,"YOffSet":3,"ZOffSet":0,"Block":"minecraft:bedrock", "Falling":false, "RelativeToPlayer":true},
      {"XOffSet":1,"YOffSet":3,"ZOffSet":0,"Block":"minecraft:air", "Falling":false, "delay":200, "RelativeToPlayer":true},
      {"XOffSet":2,"YOffSet":3,"ZOffSet":0,"Block":"minecraft:bedrock", "Falling":false, "RelativeToPlayer":true},
      {"XOffSet":2,"YOffSet":3,"ZOffSet":0,"Block":"minecraft:air", "Falling":false, "delay":200, "RelativeToPlayer":true},

      {"XOffSet":-2,"YOffSet":3,"ZOffSet":1,"Block":"minecraft:bedrock", "Falling":false, "RelativeToPlayer":true},
      {"XOffSet":-2,"YOffSet":3,"ZOffSet":1,"Block":"minecraft:air", "Falling":false, "delay":200, "RelativeToPlayer":true},
      {"XOffSet":-1,"YOffSet":3,"ZOffSet":1,"Block":"minecraft:bedrock", "Falling":false, "RelativeToPlayer":true},
      {"XOffSet":-1,"YOffSet":3,"ZOffSet":1,"Block":"minecraft:air", "Falling":false, "delay":200, "RelativeToPlayer":true},
      {"XOffSet":0,"YOffSet":3,"ZOffSet":1,"Block":"minecraft:bedrock", "Falling":false, "RelativeToPlayer":true},
      {"XOffSet":0,"YOffSet":3,"ZOffSet":1,"Block":"minecraft:air", "Falling":false, "delay":200, "RelativeToPlayer":true},
      {"XOffSet":1,"YOffSet":3,"ZOffSet":1,"Block":"minecraft:bedrock", "Falling":false, "RelativeToPlayer":true},
      {"XOffSet":1,"YOffSet":3,"ZOffSet":1,"Block":"minecraft:air", "Falling":false, "delay":200, "RelativeToPlayer":true},
      {"XOffSet":2,"YOffSet":3,"ZOffSet":1,"Block":"minecraft:bedrock", "Falling":false, "RelativeToPlayer":true},
      {"XOffSet":2,"YOffSet":3,"ZOffSet":1,"Block":"minecraft:air", "Falling":false, "delay":200, "RelativeToPlayer":true},

      {"XOffSet":-2,"YOffSet":3,"ZOffSet":2,"Block":"minecraft:bedrock", "Falling":false, "RelativeToPlayer":true},
      {"XOffSet":-2,"YOffSet":3,"ZOffSet":2,"Block":"minecraft:air", "Falling":false, "delay":200, "RelativeToPlayer":true},
      {"XOffSet":-1,"YOffSet":3,"ZOffSet":2,"Block":"minecraft:bedrock", "Falling":false, "RelativeToPlayer":true},
      {"XOffSet":-1,"YOffSet":3,"ZOffSet":2,"Block":"minecraft:air", "Falling":false, "delay":200, "RelativeToPlayer":true},
      {"XOffSet":0,"YOffSet":3,"ZOffSet":2,"Block":"minecraft:bedrock", "Falling":false, "RelativeToPlayer":true},
      {"XOffSet":0,"YOffSet":3,"ZOffSet":2,"Block":"minecraft:air", "Falling":false, "delay":200, "RelativeToPlayer":true},
      {"XOffSet":1,"YOffSet":3,"ZOffSet":2,"Block":"minecraft:bedrock", "Falling":false, "RelativeToPlayer":true},
      {"XOffSet":1,"YOffSet":3,"ZOffSet":2,"Block":"minecraft:air", "Falling":false, "delay":200, "RelativeToPlayer":true},
      {"XOffSet":2,"YOffSet":3,"ZOffSet":2,"Block":"minecraft:bedrock", "Falling":false, "RelativeToPlayer":true},
      {"XOffSet":2,"YOffSet":3,"ZOffSet":2,"Block":"minecraft:air", "Falling":false, "delay":200, "RelativeToPlayer":true},

      {"XOffSet":-2,"YOffSet":1,"ZOffSet":2,"Block":"minecraft:bedrock", "Falling":false, "RelativeToPlayer":true},
      {"XOffSet":-2,"YOffSet":1,"ZOffSet":2,"Block":"minecraft:air", "Falling":false, "delay":200, "RelativeToPlayer":true},
      {"XOffSet":-1,"YOffSet":1,"ZOffSet":2,"Block":"minecraft:bedrock", "Falling":false, "RelativeToPlayer":true},
      {"XOffSet":-1,"YOffSet":1,"ZOffSet":2,"Block":"minecraft:air", "Falling":false, "delay":200, "RelativeToPlayer":true},
      {"XOffSet":0,"YOffSet":1,"ZOffSet":2,"Block":"minecraft:bedrock", "Falling":false, "RelativeToPlayer":true},
      {"XOffSet":0,"YOffSet":1,"ZOffSet":2,"Block":"minecraft:air", "Falling":false, "delay":200, "RelativeToPlayer":true},
      {"XOffSet":1,"YOffSet":1,"ZOffSet":2,"Block":"minecraft:bedrock", "Falling":false, "RelativeToPlayer":true},
      {"XOffSet":1,"YOffSet":1,"ZOffSet":2,"Block":"minecraft:air", "Falling":false, "delay":200, "RelativeToPlayer":true},
      {"XOffSet":2,"YOffSet":1,"ZOffSet":2,"Block":"minecraft:bedrock", "Falling":false, "RelativeToPlayer":true},
      {"XOffSet":2,"YOffSet":1,"ZOffSet":2,"Block":"minecraft:air", "Falling":false, "delay":200, "RelativeToPlayer":true},

      {"XOffSet":-2,"YOffSet":1,"ZOffSet":-2,"Block":"minecraft:bedrock", "Falling":false, "RelativeToPlayer":true},
      {"XOffSet":-2,"YOffSet":1,"ZOffSet":-2,"Block":"minecraft:air", "Falling":false, "delay":200, "RelativeToPlayer":true},
      {"XOffSet":-1,"YOffSet":1,"ZOffSet":-2,"Block":"minecraft:bedrock", "Falling":false, "RelativeToPlayer":true},
      {"XOffSet":-1,"YOffSet":1,"ZOffSet":-2,"Block":"minecraft:air", "Falling":false, "delay":200, "RelativeToPlayer":true},
      {"XOffSet":0,"YOffSet":1,"ZOffSet":-2,"Block":"minecraft:bedrock", "Falling":false, "RelativeToPlayer":true},
      {"XOffSet":0,"YOffSet":1,"ZOffSet":-2,"Block":"minecraft:air", "Falling":false, "delay":200, "RelativeToPlayer":true},
      {"XOffSet":1,"YOffSet":1,"ZOffSet":-2,"Block":"minecraft:bedrock", "Falling":false, "RelativeToPlayer":true},
      {"XOffSet":1,"YOffSet":1,"ZOffSet":-2,"Block":"minecraft:air", "Falling":false, "delay":200, "RelativeToPlayer":true},
      {"XOffSet":2,"YOffSet":1,"ZOffSet":-2,"Block":"minecraft:bedrock", "Falling":false, "RelativeToPlayer":true},
      {"XOffSet":2,"YOffSet":1,"ZOffSet":-2,"Block":"minecraft:air", "Falling":false, "delay":200, "RelativeToPlayer":true},

      {"XOffSet":-2,"YOffSet":1,"ZOffSet":-2,"Block":"minecraft:bedrock", "Falling":false, "RelativeToPlayer":true},
      {"XOffSet":-2,"YOffSet":1,"ZOffSet":-2,"Block":"minecraft:air", "Falling":false, "delay":200, "RelativeToPlayer":true},
      {"XOffSet":-2,"YOffSet":1,"ZOffSet":-1,"Block":"minecraft:bedrock", "Falling":false, "RelativeToPlayer":true},
      {"XOffSet":-2,"YOffSet":1,"ZOffSet":-1,"Block":"minecraft:air", "Falling":false, "delay":200, "RelativeToPlayer":true},
      {"XOffSet":-2,"YOffSet":1,"ZOffSet":0,"Block":"minecraft:bedrock", "Falling":false, "RelativeToPlayer":true},
      {"XOffSet":-2,"YOffSet":1,"ZOffSet":0,"Block":"minecraft:air", "Falling":false, "delay":200, "RelativeToPlayer":true},
      {"XOffSet":-2,"YOffSet":1,"ZOffSet":1,"Block":"minecraft:bedrock", "Falling":false, "RelativeToPlayer":true},
      {"XOffSet":-2,"YOffSet":1,"ZOffSet":1,"Block":"minecraft:air", "Falling":false, "delay":200, "RelativeToPlayer":true},
      {"XOffSet":-2,"YOffSet":1,"ZOffSet":-2,"Block":"minecraft:bedrock", "Falling":false, "RelativeToPlayer":true},
      {"XOffSet":-2,"YOffSet":1,"ZOffSet":-2,"Block":"minecraft:air", "Falling":false, "delay":200, "RelativeToPlayer":true},

      {"XOffSet":2,"YOffSet":1,"ZOffSet":-2,"Block":"minecraft:bedrock", "Falling":false, "RelativeToPlayer":true},
      {"XOffSet":2,"YOffSet":1,"ZOffSet":-2,"Block":"minecraft:air", "Falling":false, "delay":200, "RelativeToPlayer":true},
      {"XOffSet":2,"YOffSet":1,"ZOffSet":-1,"Block":"minecraft:bedrock", "Falling":false, "RelativeToPlayer":true},
      {"XOffSet":2,"YOffSet":1,"ZOffSet":-1,"Block":"minecraft:air", "Falling":false, "delay":200, "RelativeToPlayer":true},
      {"XOffSet":2,"YOffSet":1,"ZOffSet":0,"Block":"minecraft:bedrock", "Falling":false, "RelativeToPlayer":true},
      {"XOffSet":2,"YOffSet":1,"ZOffSet":0,"Block":"minecraft:air", "Falling":false, "delay":200, "RelativeToPlayer":true},
      {"XOffSet":2,"YOffSet":1,"ZOffSet":1,"Block":"minecraft:bedrock", "Falling":false, "RelativeToPlayer":true},
      {"XOffSet":2,"YOffSet":1,"ZOffSet":1,"Block":"minecraft:air", "Falling":false, "delay":200, "RelativeToPlayer":true},
      {"XOffSet":2,"YOffSet":1,"ZOffSet":-2,"Block":"minecraft:bedrock", "Falling":false, "RelativeToPlayer":true},
      {"XOffSet":2,"YOffSet":1,"ZOffSet":-2,"Block":"minecraft:air", "Falling":false, "delay":200, "RelativeToPlayer":true}
    ]
	}
}
